uni/__init__.py
uni/__version__.py
uni/client.py
uni/exception.py
uni/response.py
uni/services/__init__.py
uni/services/messages.py
uni/services/otp.py
uni_sdk-0.3.0.dist-info/LICENSE
uni_sdk-0.3.0.dist-info/METADATA
uni_sdk-0.3.0.dist-info/WHEEL
uni_sdk-0.3.0.dist-info/top_level.txt
uni_sdk-0.3.0.dist-info/RECORD
