Metadata-Version: 2.1
Name: uni-sdk
Version: 0.3.0
Summary: The official Unimatrix SDK for Python.
Home-page: https://github.com/unimtx/uni-python-sdk
Author: Unimatrix
Author-email: dev@unimtx.com
License: MIT
Project-URL: Homepage, https://unimtx.com
Project-URL: Documentation, https://www.unimtx.com/docs
Project-URL: Repository, https://github.com/unimtx/uni-python-sdk
Keywords: unimatrix,unisdk,sms,messaging,2fa,otp,verification,sdk,api
Classifier: License :: OSI Approved :: MIT License
Classifier: Programming Language :: Python
Classifier: Programming Language :: Python :: 3
Classifier: Programming Language :: Python :: 3.6
Classifier: Programming Language :: Python :: Implementation :: CPython
Classifier: Programming Language :: Python :: Implementation :: PyPy
Requires-Python: >=3.6.0
License-File: LICENSE
